setup.py
ExcelConverter.egg-info/PKG-INFO
ExcelConverter.egg-info/SOURCES.txt
ExcelConverter.egg-info/dependency_links.txt
ExcelConverter.egg-info/requires.txt
ExcelConverter.egg-info/top_level.txt
converter/__init__.py
converter/excel_compiler.py
converter/excel_lib.py
converter/excel_node.py
converter/excel_util.py
converter/excel_wrapper.py
converter/tokenizer.py
converter/version.py