Metadata-Version: 1.1
Name: ExcelConverter
Version: 0.1.35
Summary: A library for compiling excel spreadsheets to python code
Home-page: UNKNOWN
Author: Bydehand.com
Author-email: info@bydehand.com
License: UNKNOWN
Platform: UNKNOWN
Classifier: Intended Audience :: Developers
